{
  "customerName": "Admin",
  "customerAssetsFolder" : "adminportal",
  "version" : "8",
  "useShout": false,
  "host": "https://hq.coresystems.hu:9610/",
  "subpath": "flask",
  "authenticationMode" : "SSOPool",
  "camNamespace" : "",
  "noauthUser" : "",
  "noauthPwd" : "",
  "sessionExpiresInMinutes" : 20,
  "authenticationBridge" : "https://hq.coresystems.hu:9610/flasksso/auth.aspx",
  "apiLogout" : "",
  "logout" : "",
  "restRequestDebugFlag" : false,
  "tm1ApiHost" : "https://hq.coresystems.hu:9610/flask/pool",
  "tm1ApiSubPath" : "/api/v1/",
  "tm1ExecuteMDX" : "ExecuteMDX?",
  "MDXUrl" : "https://hq.coresystems.hu:9610/flask/pool/api/v1/ExecuteMDX?",
  "defaultMDXQuery" : "https://hq.coresystems.hu:9610/flask/pool/api/v1/ExecuteMDX?$expand=Cells($select=Ordinal,Value)",
  "SideBar" : "adminPortalSideBar",
  "MainPage" : "adminPortalMain",
  "pool" : {
    "users": ["CAMNamespace b3JhdmVjei50YW1hczpUb21pTmV3UGFzczEyMTIlOmtub3dsZWRnZXNlZWQ=", "CAMNamespace c292ZWdqYXJ0by5hbmRyYXM6U000REFzZGYxMjM0JTprbm93bGVkZ2VzZWVk"],
    "target" : "http://localhost:5280"
  },
  "sso": {
    "userCAMNamespace": "CAMNamespace b3JhdmVjei50YW1hczpUb21pTmV3UGFzczEyMTIlOmtub3dsZWRnZXNlZWQ=",
    "getUserUrl": "https://localhost:5350/api/v1/ExecuteMDX?$expand=Cells($select=Ordinal,Value)",
    "getUserBody": "{\"MDX\":\"SELECT { [}ElementAttributes_zSYS Analogic UserPool].[Token], [}ElementAttributes_zSYS Analogic UserPool].[Authorized]} on COLUMNS FROM [}ElementAttributes_zSYS Analogic UserPool] WHERE ([zSYS Analogic UserPool].[$username])\"}",
    "putUserUrl": "https://localhost:5350/api/v1/Dimensions('zSYSAnalogicUserPool')/Hierarchies('zSYSAnalogicUserPool')/Elements",
    "putUserBody": "{\"Name\":\"$username\"}",
    "putTokenUrl": "https://localhost:5350/api/v1/Cubes('%7DElementAttributes_zSYSAnalogicUserPool')/tm1.Update",
    "putTokenBody": "{\"Cells\": [{\"Tuple@odata.bind\": [\"Dimensions('}ElementAttributes_zSYS Analogic UserPool')/Hierarchies('}ElementAttributes_zSYS Analogic UserPool')/Elements('Token')\",\"Dimensions('zSYS Analogic UserPool')/Hierarchies('zSYS Analogic UserPool')/Elements('$username')\"]}],\"Value\": \"$token\"}",
    "additionalPostUrl1": "",
    "additionalPostBody1": "",
    "additionalPostUrl2": "",
    "additionalPostBody2": "",
    "secret": "db3OIsj+BXE9NZDy0t8W3TcNekrF+2d/1sFnWG4HnV8TZY30iTOdtVWJG8abWvB1GlOgJuQZdcF2Luqm/hccMw==",
    "appHost": "https://hq.coresystems.hu:9610"
  }
  
}